genice2_extra/__init__.py
genice2_extra-2.3.dist-info/METADATA
genice2_extra-2.3.dist-info/WHEEL
genice2_extra-2.3.dist-info/RECORD
