Metadata-Version: 2.1
Name: genice2-extra
Version: 2.3
Summary: Official extra format plugins for GenIce2.
License: MIT
Author: vitroid
Author-email: vitroid@gmail.com
Requires-Python: >=3.9,<4.0
Classifier: License :: OSI Approved :: MIT License
Classifier: Programming Language :: Python :: 3
Classifier: Programming Language :: Python :: 3.9
Classifier: Programming Language :: Python :: 3.10
Classifier: Programming Language :: Python :: 3.11
Classifier: Programming Language :: Python :: 3.12
Requires-Dist: genice2-cage (>=2.3)
Requires-Dist: genice2-cif (>=2.2)
Requires-Dist: genice2-mdanalysis (>=0.7)
Requires-Dist: genice2-svg (>=2.4.1)
